lhctodd/__init__.py
lhctodd/model.py
lhctodd/theory.py
lhctodd/tools.py
lhctodd/.ipynb_checkpoints/model-checkpoint.py
lhctodd/.ipynb_checkpoints/theory-checkpoint.py
lhctodd/.ipynb_checkpoints/tools-checkpoint.py
lhctodd/data/alpha_s.csv
lhctodd/data/.ipynb_checkpoints/alpha_s-checkpoint.csv
lhctodd/data/darkmatter-data/data.mdb
lhctodd/data/darkmatter-data/lock.mdb
lhctodd-0.1.2.dist-info/LICENSE
lhctodd-0.1.2.dist-info/METADATA
lhctodd-0.1.2.dist-info/WHEEL
lhctodd-0.1.2.dist-info/top_level.txt
lhctodd-0.1.2.dist-info/RECORD
